Metadata-Version: 1.0
Name: probabis
Version: 0.1
Summary: Gaussian and Binomial distributions
Home-page: UNKNOWN
Author: Alvaro Montoya
Author-email: ajaltamiranomontoya@gmail.com
License: UNKNOWN
Platform: UNKNOWN
